[
  {
    "lane_id": "right_carriageway_lane1",
    "carriageway": "right_carriageway",
    "lane_index": 1,
    "direction": "toward_camera",
    "left_boundary": {
      "x_bottom": 787,
      "y_bottom": 688,
      "x_top": 655,
      "y_top": 283
    },
    "right_boundary": {
      "x_bottom": 946,
      "y_bottom": 678,
      "x_top": 708,
      "y_top": 281
    },
    "width_px": 159,
    "width_m": 3.67
  },
  {
    "lane_id": "right_carriageway_lane2",
    "carriageway": "right_carriageway",
    "lane_index": 2,
    "direction": "toward_camera",
    "left_boundary": {
      "x_bottom": 946,
      "y_bottom": 678,
      "x_top": 708,
      "y_top": 281
    },
    "right_boundary": {
      "x_bottom": 1102,
      "y_bottom": 667,
      "x_top": 762,
      "y_top": 279
    },
    "width_px": 156,
    "width_m": 3.67
  },
  {
    "lane_id": "right_carriageway_lane3",
    "carriageway": "right_carriageway",
    "lane_index": 3,
    "direction": "toward_camera",
    "left_boundary": {
      "x_bottom": 1102,
      "y_bottom": 667,
      "x_top": 762,
      "y_top": 279
    },
    "right_boundary": {
      "x_bottom": 1255,
      "y_bottom": 657,
      "x_top": 815,
      "y_top": 277
    },
    "width_px": 153,
    "width_m": 3.67
  }
]